sroka/__init__.py
sroka/api/__init__.py
sroka/api/athena/__init__.py
sroka/api/athena/athena_api.py
sroka/api/athena/athena_api_helpers.py
sroka/api/ga/__init__.py
sroka/api/ga/ga.py
sroka/api/google_ad_manager/__init__.py
sroka/api/google_ad_manager/gam_api.py
sroka/api/google_bigquery/__init__.py
sroka/api/google_bigquery/bigquery_api.py
sroka/api/google_drive/__init__.py
sroka/api/google_drive/google_drive_api.py
sroka/api/google_drive/google_drive_helpers.py
sroka/api/moat/__init__.py
sroka/api/moat/moat_api.py
sroka/api/moat/moat_api_helpers.py
sroka/api/mysql/__init__.py
sroka/api/mysql/mysql.py
sroka/api/mysql/mysql_helpers.py
sroka/api/neo4j/__init__.py
sroka/api/neo4j/neo4j_api.py
sroka/api/qubole/__init__.py
sroka/api/qubole/qubole_api.py
sroka/api/qubole/query_result_file.py
sroka/api/rubicon/__init__.py
sroka/api/rubicon/rubicon_api.py
sroka/api/s3_connection/__init__.py
sroka/api/s3_connection/s3_connection_api.py
sroka/config/__init__.py
sroka/config/config.py
sroka-0.1.1.dist-info/licenses/LICENSE
sroka-0.1.1.dist-info/METADATA
sroka-0.1.1.dist-info/WHEEL
sroka-0.1.1.dist-info/top_level.txt
sroka-0.1.1.dist-info/RECORD
