Metadata-Version: 2.4
Name: sroka
Version: 0.1.1
Summary: Package for access GA, GAM, MOAT, Qubole, Athena, S3, Rubicon APIs, BigQuery, MySQL
Home-page: https://github.com/Wikia/sroka
Author: Ad Engineering FANDOM
Author-email: murbanek@fandom.com
Classifier: Programming Language :: Python :: 3
Classifier: Operating System :: OS Independent
License-File: LICENSE
Requires-Dist: boto3>=1.9.19
Requires-Dist: botocore>=1.12.19
Requires-Dist: flake8==3.7.7
Requires-Dist: google-auth-httplib2>=0.0.3
Requires-Dist: google_api_python_client>=1.6.7
Requires-Dist: google_auth_oauthlib>=0.2.0
Requires-Dist: google-cloud-bigquery>=1.24.0
Requires-Dist: googleads>=42.0.0
Requires-Dist: isort==4.3.9
Requires-Dist: lxml>=4.6.5
Requires-Dist: mysql-connector-python==9.1.0
Requires-Dist: numpy>=1.16.2
Requires-Dist: pandas>=0.24.0
Requires-Dist: pyarrow>=0.11.1
Requires-Dist: qds_sdk>=1.10.1
Requires-Dist: requests>=2.20
Requires-Dist: retrying>=1.3.3
Requires-Dist: urllib3>=1.26.18
Requires-Dist: py2neo>=4.2.0
Requires-Dist: db-dtypes
Requires-Dist: zeep>=4.2.1
Dynamic: author
Dynamic: author-email
Dynamic: classifier
Dynamic: description
Dynamic: description-content-type
Dynamic: home-page
Dynamic: license-file
Dynamic: requires-dist
Dynamic: summary
